dotevals/__init__.py
dotevals/cli.py
dotevals/concurrency.py
dotevals/decorators.py
dotevals/evaluation.py
dotevals/exceptions.py
dotevals/interactive.py
dotevals/plugin.py
dotevals/progress.py
dotevals/results.py
dotevals/runner.py
dotevals/sessions.py
dotevals/summary.py
dotevals/types.py
dotevals/datasets/__init__.py
dotevals/datasets/base.py
dotevals/datasets/registry.py
dotevals/evaluators/__init__.py
dotevals/evaluators/ast_evaluation.py
dotevals/evaluators/base.py
dotevals/evaluators/registry.py
dotevals/executors/__init__.py
dotevals/executors/base.py
dotevals/executors/batch.py
dotevals/executors/foreach.py
dotevals/executors/registry.py
dotevals/metrics/__init__.py
dotevals/metrics/base.py
dotevals/metrics/registry.py
dotevals/storage/__init__.py
dotevals/storage/base.py
dotevals/storage/json.py
dotevals/storage/registry.py
dotevals-0.28.3.dist-info/METADATA
dotevals-0.28.3.dist-info/WHEEL
dotevals-0.28.3.dist-info/entry_points.txt
dotevals-0.28.3.dist-info/top_level.txt
dotevals-0.28.3.dist-info/RECORD
