Metadata-Version: 2.4
Name: dotevals
Version: 0.28.3
Summary: Simple and robust LLM evaluations
Author: .txt
Project-URL: repository, https://github.com/dottxt-ai/dotevals
Requires-Python: >=3.10
Requires-Dist: click
Requires-Dist: pytest
Requires-Dist: rich
Requires-Dist: jsonschema
Requires-Dist: nest-asyncio
Provides-Extra: test
Requires-Dist: pytest-asyncio; extra == "test"
Requires-Dist: pytest-cov; extra == "test"
Requires-Dist: coverage[toml]>=5.1; extra == "test"
Requires-Dist: diff-cover; extra == "test"
